targ/__init__.py
targ/format.py
targ/py.typed
targ-0.4.0.dist-info/LICENSE
targ-0.4.0.dist-info/METADATA
targ-0.4.0.dist-info/WHEEL
targ-0.4.0.dist-info/top_level.txt
targ-0.4.0.dist-info/RECORD
