Metadata-Version: 2.1
Name: targ
Version: 0.4.0
Summary: Build a Python CLI for your app, just using type hints and docstrings.
Home-page: https://github.com/piccolo-orm/targ/
Author: Daniel Townsend
Author-email: dan@dantownsend.co.uk
License: MIT
Classifier: License :: OSI Approved :: MIT License
Classifier: Programming Language :: Python
Classifier: Programming Language :: Python :: 3
Classifier: Programming Language :: Python :: 3.8
Classifier: Programming Language :: Python :: 3.9
Classifier: Programming Language :: Python :: 3.10
Classifier: Programming Language :: Python :: 3.11
Classifier: Programming Language :: Python :: 3.12
Classifier: Programming Language :: Python :: Implementation :: CPython
Requires-Python: >=3.8.0
License-File: LICENSE
Requires-Dist: colorama==0.4.*
Requires-Dist: docstring-parser>=0.12
Requires-Dist: typing_inspect>=0.6.0; python_version < "3.8"
